picture2pixel/__init__.py
picture2pixel/convert2image.py
picture2pixel/convert2mem.py
picture2pixel/convert2picture.py
picture2pixel/convert2pixel.py
picture2pixel/image_processing.py
picture2pixel/verilog_generator.py
picture2pixel/tests/__init__.py
picture2pixel/tests/test_picture2pixel.py
picture2pixel/tests/test_pixel2picture.py
picture2pixel-2.0.0.dist-info/LICENSE
picture2pixel-2.0.0.dist-info/METADATA
picture2pixel-2.0.0.dist-info/WHEEL
picture2pixel-2.0.0.dist-info/top_level.txt
picture2pixel-2.0.0.dist-info/RECORD
