Metadata-Version: 2.1
Name: picture2pixel
Version: 2.0.0
Summary: A package for processing images and generating Verilog code for FPGA
Home-page: https://www.comp.nus.edu.sg/~guoyi/project/picture2pixel/
Author: Chen Guoyi
Author-email: guoyi@comp.nus.edu.sg
License: MIT
Classifier: Development Status :: 3 - Alpha
Classifier: Intended Audience :: Developers
Classifier: License :: OSI Approved :: MIT License
Classifier: Programming Language :: Python :: 3
Classifier: Programming Language :: Python :: 3.7
Classifier: Programming Language :: Python :: 3.8
Classifier: Programming Language :: Python :: 3.9
Requires-Python: >=3.6
License-File: LICENSE
Requires-Dist: numpy
Requires-Dist: matplotlib
Requires-Dist: imageio
Requires-Dist: Pillow
